{
  "items": [
    {
      "type": "file",
      "ctime": 1718136715641,
      "path": "Otro_Espacio/Todo_Software/Entorno de Desarrollo/Karabiner/Karabiner Hammerspoon y Hyper Key para Atajos en MacOS.md"
    },
    {
      "type": "file",
      "ctime": 1725468888784,
      "path": "Otro_Espacio/Todo_Software/Entorno de Desarrollo/Sublime_Text_-_Atajos_de_Teclado.md",
      "title": "Atajos de teclado en Sublime Text"
    },
    {
      "type": "file",
      "ctime": 1725674425463,
      "path": "Otro_Espacio/Todo_Software/Desarrollo_de_Software/Temas_de_Git.md",
      "title": "Git Worktree"
    },
    {
      "type": "file",
      "ctime": 1739395155934,
      "path": "DevAsPros/Cinco Tokens de Esfuerzo.md"
    },
    {
      "type": "file",
      "ctime": 1741553768434,
      "path": "Otro_Espacio/Estado y Ubicación de los Respaldos.md",
      "title": "Sobre los Respaldos"
    },
    {
      "type": "file",
      "ctime": 1746889606425,
      "path": "DevAsPros/Cash_Flow/Apuntes_Ciclo_22_-_Cron_Sidekiq.md",
      "title": "Apuntes Sidekiq como Cron"
    },
    {
      "type": "file",
      "ctime": 1746889633685,
      "path": "Otro_Espacio/Todo_Software/Entorno de Desarrollo/Zed Editor - Atajos de Teclado.md"
    },
    {
      "type": "file",
      "ctime": 1750277120683,
      "path": "Luna/Grafana_Queries.md"
    },
    {
      "type": "file",
      "ctime": 1756129891416,
      "path": "Otro_Espacio/Blog/Nuevo Enfoque para el Blog 💡.md"
    },
    {
      "type": "file",
      "ctime": 1760480493744,
      "path": "Luna/Backend/Edge Enums que Importan 🔑.md",
      "title": "Enums en Edge"
    }
  ]
}